README.md
setup.cfg
setup.py
tweetple/AuxTweetPle.py
tweetple/TweetPle.py
tweetple/TwitterFullArchive.py
tweetple/_init_.py
tweetple.egg-info/PKG-INFO
tweetple.egg-info/SOURCES.txt
tweetple.egg-info/dependency_links.txt
tweetple.egg-info/not-zip-safe
tweetple.egg-info/top_level.txt