Metadata-Version: 1.0
Name: tweetple
Version: 0.13006
Summary: A python wrapper for users of the Academic Research product track
Home-page: https://github.com/dapivei/tweetple
Author: Daniela Pinto Veizaga
Author-email: danielapintoveizaga@gmail.com
License: UNKNOWN
Platform: UNKNOWN
